injeild_repl_ru/__init__.py
injeild_repl_ru/commands.py
injeild_repl_ru/core.py
injeild_repl_ru-1.0.0.dist-info/METADATA
injeild_repl_ru-1.0.0.dist-info/WHEEL
injeild_repl_ru-1.0.0.dist-info/top_level.txt
injeild_repl_ru-1.0.0.dist-info/RECORD
