Metadata-Version: 2.4
Name: injeild_repl_ru
Version: 1.0.0
Summary: Русская обёртка Python для INJEILD v9.1
Author: Александр
Requires-Python: >=3.7
Dynamic: author
Dynamic: requires-python
Dynamic: summary
